etf_strategy/__init__.py
etf_strategy/etf_strategy.py
etf_strategy-0.1.5.dist-info/METADATA
etf_strategy-0.1.5.dist-info/WHEEL
etf_strategy-0.1.5.dist-info/top_level.txt
etf_strategy-0.1.5.dist-info/RECORD
