Metadata-Version: 2.4
Name: etf-strategy
Version: 0.1.5
Summary: ETF策略工具包
Author: Jack
Requires-Python: >=3.7
Requires-Dist: pandas
Requires-Dist: numpy
Dynamic: author
Dynamic: requires-dist
Dynamic: requires-python
Dynamic: summary
